digital_employee_core/__init__.py
digital_employee_core/agents/__init__.py
digital_employee_core/agents/mom_agent.md
digital_employee_core/agents/mom_agent.py
digital_employee_core/agents/mom_docs_agent.py
digital_employee_core/agents/mom_docs_extension.md
digital_employee_core/agents/mom_email_extension.md
digital_employee_core/agents/mom_mail_agent.py
digital_employee_core/config_templates/__init__.py
digital_employee_core/config_templates/defaults.yaml
digital_employee_core/config_templates/loader.py
digital_employee_core/config_templates/mcp_configs.yaml
digital_employee_core/config_templates/tool_configs.yaml
digital_employee_core/configuration/__init__.py
digital_employee_core/configuration/agent_configuration.py
digital_employee_core/configuration/configuration.py
digital_employee_core/connectors/__init__.py
digital_employee_core/connectors/mcps/__init__.py
digital_employee_core/connectors/mcps/github_mcps.py
digital_employee_core/connectors/mcps/google_mcps.py
digital_employee_core/connectors/mcps/meemo_mcps.py
digital_employee_core/connectors/mcps/sql_mcps.py
digital_employee_core/connectors/tools/__init__.py
digital_employee_core/connectors/tools/data_tools.py
digital_employee_core/connectors/tools/development_tools.py
digital_employee_core/connectors/tools/file_tools.py
digital_employee_core/connectors/tools/glchat_qiscus_whatsapp_tools.py
digital_employee_core/connectors/tools/messaging_tools.py
digital_employee_core/connectors/tools/utility_tools.py
digital_employee_core/connectors/tools/web_tools.py
digital_employee_core/constants/__init__.py
digital_employee_core/constants/models.py
digital_employee_core/digital_employee/__init__.py
digital_employee_core/digital_employee/config_propagation.py
digital_employee_core/digital_employee/dependencies/__init__.py
digital_employee_core/digital_employee/dependencies/dependency_bundle.py
digital_employee_core/digital_employee/dependencies/types.py
digital_employee_core/digital_employee/digital_employee.py
digital_employee_core-0.0.20.dist-info/METADATA
digital_employee_core-0.0.20.dist-info/WHEEL
digital_employee_core-0.0.20.dist-info/RECORD
