Metadata-Version: 2.4
Name: digital-employee-core
Version: 0.0.20
Summary: 
Author: Digital Employee Team
Requires-Python: >=3.11,<3.13
Classifier: Programming Language :: Python :: 3
Classifier: Programming Language :: Python :: 3.11
Classifier: Programming Language :: Python :: 3.12
Requires-Dist: aip-agents-binary (>=0.6.3,<0.7.0)
Requires-Dist: apscheduler (>=3.11.0,<4.0.0)
Requires-Dist: authlib (>=1.6.1,<2.0.0)
Requires-Dist: email-validator (>=2.3.0,<3.0.0)
Requires-Dist: fastapi (>=0.120.0,<0.121.0)
Requires-Dist: glaip-sdk[local,memory,privacy] (>=0.7.25)
Requires-Dist: gllm-plugin-binary (>=0.0.7,<0.0.8)
Requires-Dist: google-api-python-client (>=2.0.0,<3.0.0)
Requires-Dist: omegaconf (>=2.3.0,<3.0.0)
Requires-Dist: opentelemetry-instrumentation-httpx
Requires-Dist: opentelemetry-instrumentation-requests
Requires-Dist: pre-commit (>=4.2.0,<5.0.0)
Requires-Dist: python-dotenv (>=1.0.0,<2.0.0)
Requires-Dist: python-multipart (>=0.0.20,<0.0.21)
Requires-Dist: pyyaml (>=6.0.3,<7.0.0)
Requires-Dist: requests (>=2.32.0,<3.0.0)
Requires-Dist: ruff (>=0.14.0,<0.15.0)
Requires-Dist: uvicorn (>=0.34.0,<0.35.0)
